README.md
setup.cfg
setup.py
qportalwrapper/__init__.py
qportalwrapper/__main__.py
qportalwrapper/datatypes.py
qportalwrapper/enums.py
qportalwrapper/qportalwrapper.py
qportalwrapper.egg-info/PKG-INFO
qportalwrapper.egg-info/SOURCES.txt
qportalwrapper.egg-info/dependency_links.txt
qportalwrapper.egg-info/requires.txt
qportalwrapper.egg-info/top_level.txt