Metadata-Version: 2.1
Name: qportalwrapper
Version: 1.0.0
Summary: An unofficial Python wrapper for interfacing with Q Portal
Home-page: https://gitlab.com/bbworld1/qportalwrapper
Author: Vincent Wang
Author-email: vwangsf@gmail.com
License: UNKNOWN
Keywords: qportal qconnection qstudent
Platform: UNKNOWN
Classifier: Development Status :: 4 - Beta
Classifier: Intended Audience :: Developers
Classifier: License :: OSI Approved :: GNU General Public License (GPL)
Classifier: Programming Language :: Python :: 3
